{
  "resourceType" : "StructureDefinition",
  "id" : "ST-r2b",
  "language" : "en",
  "text" : {
    "status" : "generated",
    "div" : "<div xmlns=\"http://www.w3.org/1999/xhtml\">\n      <p>A character string data type variant (ST-r2b) that uses a value attribute rather than element content. This datatype is primarily used to handle version numbers and other string values in CDA documents where the data is stored as an XML attribute.</p>\n    </div>"
  },
  "extension" : [{
    "url" : "http://hl7.org/fhir/tools/StructureDefinition/logical-target",
    "_valueBoolean" : {
      "extension" : [{
        "url" : "http://hl7.org/fhir/StructureDefinition/data-absent-reason",
        "valueCode" : "not-applicable"
      }]
    }
  },
  {
    "url" : "http://hl7.org/fhir/tools/StructureDefinition/xml-namespace",
    "valueUri" : "urn:hl7-org:v3"
  },
  {
    "url" : "http://hl7.org/fhir/tools/StructureDefinition/xml-name",
    "valueString" : "ST.r2b"
  },
  {
    "url" : "http://hl7.org/fhir/tools/StructureDefinition/logical-container",
    "valueUri" : "http://hl7.org/cda/stds/core/StructureDefinition/ClinicalDocument"
  }],
  "url" : "http://hl7.org/cda/stds/core/StructureDefinition/ST-r2b",
  "version" : "2.0.0-sd-202510-matchbox-patch",
  "name" : "ST-r2b",
  "title" : "ST-r2b: CharacterString with Value Attribute (V3 Data Type)",
  "status" : "active",
  "experimental" : false,
  "date" : "2025-10-28T21:58:07+01:00",
  "publisher" : "Health Level 7",
  "contact" : [{
    "name" : "HL7 International - Structured Documents",
    "telecom" : [{
      "system" : "url",
      "value" : "http://www.hl7.org/Special/committees/structure"
    },
    {
      "system" : "email",
      "value" : "structdog@lists.HL7.org"
    }]
  }],
  "description" : "A character string data type variant that uses a value attribute rather than element content. This datatype is primarily used to handle version numbers and other string values in CDA documents where the data is stored as an XML attribute.",
  "fhirVersion" : "5.0.0",
  "mapping" : [{
    "identity" : "rim",
    "uri" : "http://hl7.org/v3",
    "name" : "RIM Mapping"
  }],
  "kind" : "logical",
  "abstract" : false,
  "type" : "http://hl7.org/cda/stds/core/StructureDefinition/ST-r2b",
  "baseDefinition" : "http://hl7.org/cda/stds/core/StructureDefinition/ANY",
  "derivation" : "specialization",
  "snapshot" : {
    "extension" : [{
      "url" : "http://hl7.org/fhir/tools/StructureDefinition/snapshot-base-version",
      "valueString" : "2.0.0-sd-202510-matchbox-patch"
    }],
    "element" : [{
      "id" : "ST-r2b",
      "path" : "ST-r2b",
      "short" : "Base for all types and resources",
      "definition" : "A character string data type variant that uses a value attribute rather than element content.",
      "min" : 1,
      "max" : "*",
      "base" : {
        "path" : "Base",
        "min" : 0,
        "max" : "*"
      },
      "constraint" : [{
        "key" : "value-null",
        "severity" : "error",
        "human" : "value and nullFlavor are mutually exclusive (one must be present)",
        "expression" : "(value | nullFlavor).count() = 1"
      }],
      "isModifier" : false,
      "mapping" : [{
        "identity" : "rim",
        "map" : "n/a"
      }]
    },
    {
      "id" : "ST-r2b.nullFlavor",
      "path" : "ST-r2b.nullFlavor",
      "representation" : ["xmlAttr"],
      "label" : "Exceptional Value Detail",
      "definition" : "If a value is an exceptional value (NULL-value), this specifies in what way and why proper information is missing.",
      "min" : 0,
      "max" : "1",
      "base" : {
        "path" : "ANY.nullFlavor",
        "min" : 0,
        "max" : "1"
      },
      "type" : [{
        "code" : "code",
        "profile" : ["http://hl7.org/cda/stds/core/StructureDefinition/cs-simple"]
      }],
      "binding" : {
        "strength" : "required",
        "valueSet" : "http://hl7.org/cda/stds/core/ValueSet/CDANullFlavor"
      }
    },
    {
      "id" : "ST-r2b.value",
      "path" : "ST-r2b.value",
      "representation" : ["xmlAttr"],
      "label" : "Value",
      "definition" : "The string value stored as an XML attribute rather than element content.",
      "min" : 0,
      "max" : "1",
      "base" : {
        "path" : "ST-r2b.value",
        "min" : 0,
        "max" : "1"
      },
      "type" : [{
        "code" : "string",
        "profile" : ["http://hl7.org/cda/stds/core/StructureDefinition/st-simple"]
      }]
    }]
  },
  "differential" : {
    "element" : [{
      "id" : "ST-r2b",
      "path" : "ST-r2b",
      "definition" : "A character string data type variant that uses a value attribute rather than element content.",
      "min" : 1,
      "max" : "*",
      "constraint" : [{
        "key" : "value-null",
        "severity" : "error",
        "human" : "value and nullFlavor are mutually exclusive (one must be present)",
        "expression" : "(value | nullFlavor).count() = 1"
      }]
    },
    {
      "id" : "ST-r2b.value",
      "path" : "ST-r2b.value",
      "representation" : ["xmlAttr"],
      "label" : "Value",
      "definition" : "The string value stored as an XML attribute rather than element content.",
      "min" : 0,
      "max" : "1",
      "type" : [{
        "code" : "string",
        "profile" : ["http://hl7.org/cda/stds/core/StructureDefinition/st-simple"]
      }]
    }]
  }
}